{
  "symbol": "CHFJPY",
  "timeframe": "1m",
  "architecture": "mlp",
  "input_dim": 30,
  "n_classes": 3,
  "selected_features": [
    "kurtosis",
    "stochastic_d",
    "obv",
    "session_volatility",
    "hurst_exponent",
    "pivot_point",
    "jump_component",
    "bipower_variation",
    "synthetic_spread",
    "macd_histogram",
    "atr_normalized",
    "parkinson_volatility",
    "value_factor",
    "liquidity_score",
    "realized_vol_60m",
    "bollinger_percent_b",
    "macd_signal",
    "sma_ratio_10_20",
    "bollinger_bandwidth",
    "volatility_factor",
    "rsi_normalized",
    "adx",
    "momentum_factor",
    "spread_percentile",
    "volatility_of_vol",
    "realized_vol_5m",
    "williams_r_normalized",
    "standardized_range",
    "obv_normalized",
    "mfi_normalized"
  ],
  "train_samples": 6955,
  "val_samples": 1490,
  "test_samples": 1491,
  "timestamp": "20251208_131749",
  "version": "v1"
}